Workbook

Sheet Guide
A1: Echo Labs, Inc. · three-statement operating model
A2: Actuals 2025-10 to 2026-09 from the ledger; forecast 2026-10 to 2028-03 by formula.
A4: How it links
A5: 1. Assumptions: pick Base, Upside or Downside in C4. The Live column picks that scenario's drivers with INDEX/MATCH.
A6: 2. P&L: revenue grows from last month by the growth driver; costs are driver percentages or roll forward with growth and the hiring plan.
A7: 3. Balance sheet: receivables and payables from DSO and DPO; fixed assets roll forward with capex and depreciation; retained earnings roll forward with P&L net income; cash comes from the cash flow statement.
A8: 4. Cash flow (indirect): net income + depreciation - change in receivables + change in payables and payroll liabilities, less capex, plus any equity raised. Closing cash feeds the balance sheet.
A9: 5. KPIs: burn, runway, ARR, CAC payback and margins, all formulas on the statements.
A10: 6. Checks: the balance sheet balances, cash ties, net income ties to the ledger, retained earnings roll forward: TRUE in every month.
A12: Colour code
A13: Blue: input (a ledger actual or an assumption you can change).
A14: Black: formula on the same sheet.
... A19: One cash account and one company (entities consolidated); no debt drawn; no interest income; tax shown at the cash rate (US losses carried forward shelter profits). Edit the drivers or enter an equity raise on the Cash flow sheet to test a plan.

Sheet Assumptions
A1: Echo Labs, Inc.
A2: Assumptions
A3: Change the scenario in C4: every forecast cell on every sheet recalculates.
A4: Scenario | C4: Base
A6: Driver | B6: Unit | C6: Base | D6: Upside | E6: Downside | F6: Live (selected) | G6: Source
A7: Usage revenue growth per month | B7: % | C7: 0.0274 | D7: 0.0374 | E7: -0.0086 | F7: =IF(Sensitivity!$C$5="",INDEX(C7:E7,MATCH($C$4,$C$6:$E$6,0)),Sensitivity!$C$5) | G7: Base: compound growth over the last 12 months; downside: the last 6 months' slowdown persists, minus 1 point
A8: Services revenue growth per month | B8: % | C8: 0 | D8: 0.01 | E8: -0.02 | F8: =INDEX(C8:E8,MATCH($C$4,$C$6:$E$6,0)) | G8: Project services held flat in the base case
A9: Refunds and credits, % of usage revenue (negative) | B9: % | C9: 0 | D9: 0 | E9: -0.0001 | F9: =INDEX(C9:E9,MATCH($C$4,$C$6:$E$6,0)) | G9: Last 12 months
A10: GPU compute, % of usage revenue | B10: % | C10: 0.3302 | D10: 0.3102 | E10: 0.3602 | F10: =INDEX(C10:E10,MATCH($C$4,$C$6:$E$6,0)) | G10: Last 3 months; upside = better GPU utilisation
A11: Other cost of revenue, % of revenue | B11: % | C11: 0.0152 | D11: 0.0152 | E11: 0.0152 | F11: =INDEX(C11:E11,MATCH($C$4,$C$6:$E$6,0)) | G11: Last 3 months: hosting, payment fees, project costs
A12: Hiring plan executed | B12: % | C12: 1 | D12: 1 | E12: 0 | F12: =INDEX(C12:E12,MATCH($C$4,$C$6:$E$6,0)) | G12: Share of the hiring plan (Assumptions, rows below) that is hired; downside = freeze
A13: Non-payroll opex growth per month | B13: % | C13: 0.0184 | D13: 0.0234 | E13: 0.0184 | F13: =IF(Sensitivity!$C$6="",INDEX(C13:E13,MATCH($C$4,$C$6:$E$6,0)),Sensitivity!$C$6) | G13: Base: compound growth over the last 12 months
A14: Sales and marketing, % of operating expenses | B14: % | C14: 0.1782 | D14: 0.1782 | E14: 0.1782 | F14: =INDEX(C14:E14,MATCH($C$4,$C$6:$E$6,0)) | G14: Sales department share of opex, last 3 months
A15: Capital expenditure per month | B15: USD | C15: 111666.67 | D15: 111666.67 | E15: 55833.33 | F15: =INDEX(C15:E15,MATCH($C$4,$C$6:$E$6,0)) | G15: Average of the last 12 months; downside halves it
A16: Useful life of new capex (months) | B16: months | C16: 36 | D16: 36 | E16: 36 | F16: =INDEX(C16:E16,MATCH($C$4,$C$6:$E$6,0)) | G16: Straight line, from the month after purchase
A17: Days sales outstanding | B17: days | C17: 56.4 | D17: 51.4 | E17: 66.4 | F17: =INDEX(C17:E17,MATCH($C$4,$C$6:$E$6,0)) | G17: AR / revenue x 30 at the last close
A18: Days payable outstanding | B18: days | C18: 46.5 | D18: 46.5 | E18: 41.5 | F18: =INDEX(C18:E18,MATCH($C$4,$C$6:$E$6,0)) | G18: AP / (cost of revenue + non-payroll opex) x 30
A19: Payroll liabilities, % of monthly payroll | B19: % | C19: 0.4679 | D19: 0.4679 | E19: 0.4679 | F19: =INDEX(C19:E19,MATCH($C$4,$C$6:$E$6,0)) | G19: Payroll taxes and benefits payable at the last close
A20: Cash tax rate on positive pre-tax income | B20: % | C20: 0 | D20: 0 | E20: 0 | F20: =INDEX(C20:E20,MATCH($C$4,$C$6:$E$6,0)) | G20: US losses carried forward shelter profits in the forecast window (Controller page, ASC 740)
A21: Minimum cash (treasury policy) | B21: USD | C21: 3000000 | D21: 3000000 | E21: 3000000 | F21: =INDEX(C21:E21,MATCH($C$4,$C$6:$E$6,0)) | G21: seeds.treasury_policy MIN-CASH
A22: New customers per month | B22: count | C22: 3.33 | D22: 5 | E22: 1.67 | F22: =INDEX(C22:E22,MATCH($C$4,$C$6:$E$6,0)) | G22: Last 3 months' average; drives CAC and active customers
A23: Logo churn per month | B23: % | C23: 0.0598 | D23: 0.0448 | E23: 0.0747 | F23: =INDEX(C23:E23,MATCH($C$4,$C$6:$E$6,0)) | G23: Last 3 months' average
A25: Hiring plan (open and approved roles)
A26: Month | C26: 2026-10 | D26: 2026-11 | E26: 2026-12 | F26: 2027-01 | G26: 2027-02 | H26: 2027-03 | I26: 2027-04 | J26: 2027-05 | K26: 2027-06 | L26: 2027-07 | M26: 2027-08 | N26: 2027-09 | O26: 2027-10 | P26: 2027-11 | Q26: 2027-12 | R26: 2028-01 | S26: 2028-02 | T26: 2028-03
A27: New hires | C27: 0 | D27: 3 | E27: 1 | F27: 2 | G27: 1 | H27: 1 | I27: 1 | J27: 1 | K27: 1 | L27: 0 | M27: 0 | N27: 0 | O27: 0 | P27: 0 | Q27: 0 | R27: 0 | S27: 0 | T27: 0
A28: Monthly loaded cost added (salary + 7.65% payroll tax + $950 benefits) | C28: 0 | D28: 55777.92 | E28: 18443.12 | F28: 30158.12 | G28: 18443.12 | H28: 21134.38 | I28: 16200.42 | J28: 17546.04 | K28: 23377.08 | L28: 0 | M28: 0 | N28: 0 | O28: 0 | P28: 0 | Q28: 0 | R28: 0 | S28: 0 | T28: 0
A30: Outputs for the selected scenario
A31: Revenue, last forecast month | C31: ='P&L'!AG11
A32: Lowest month-end cash in the forecast | C32: =MIN('Balance sheet'!P8:AG8)
A33: Cash at the end of the forecast | C33: ='Balance sheet'!AG8
A34: Runway at the end of the forecast (months) | C34: =KPIs!AG11
A35: CAC payback at the end of the forecast (months) | C35: =KPIs!AG21
A36: EBITDA margin, last forecast month | C36: =KPIs!AG26
A37: CAC payback, last actual month (months) | C37: =KPIs!O21
A38: Model checks | C38: =Checks!C16

Sheet P&L
A1: Echo Labs, Inc.
A2: P&L
A3: Monthly income statement · actuals from the ledger (blue), forecast by formula (shaded) · USD
A5: USD | C5: 2025-09 | D5: 2025-10 | E5: 2025-11 | F5: 2025-12 | G5: 2026-01 | H5: 2026-02 | I5: 2026-03 | J5: 2026-04 | K5: 2026-05 | L5: 2026-06 | M5: 2026-07 | N5: 2026-08 | O5: 2026-09 | P5: 2026-10 | Q5: 2026-11 | R5: 2026-12 | S5: 2027-01 | T5: 2027-02 | U5: 2027-03 | V5: 2027-04 | W5: 2027-05 | X5: 2027-06 | Y5: 2027-07 | Z5: 2027-08 | AA5: 2027-09 | AB5: 2027-10 | AC5: 2027-11 | AD5: 2027-12 | AE5: 2028-01 | AF5: 2028-02 | AG5: 2028-03
C6: Opening | D6: Actual | E6: Actual | F6: Actual | G6: Actual | H6: Actual | I6: Actual | J6: Actual | K6: Actual | L6: Actual | M6: Actual | N6: Actual | O6: Actual | P6: Forecast | Q6: Forecast | R6: Forecast | S6: Forecast | T6: Forecast | U6: Forecast | V6: Forecast | W6: Forecast | X6: Forecast | Y6: Forecast | Z6: Forecast | AA6: Forecast | AB6: Forecast | AC6: Forecast | AD6: Forecast | AE6: Forecast | AF6: Forecast | AG6: Forecast
A7: Revenue
A8: Usage revenue | D8: 1171861.7 | E8: 1141548.2 | F8: 1115856.8 | G8: 1321919.9 | H8: 1250586.4 | I8: 1409590.9 | J8: 1343844.2 | K8: 1341266 | L8: 1326714.4 | M8: 1331194.6 | N8: 1323519.4 | O8: 1421467.8 | P8: =O8*(1+Assumptions!$F$7) | Q8: =P8*(1+Assumptions!$F$7) | R8: =Q8*(1+Assumptions!$F$7) | S8: =R8*(1+Assumptions!$F$7) | T8: =S8*(1+Assumptions!$F$7) | U8: =T8*(1+Assumptions!$F$7) | V8: =U8*(1+Assumptions!$F$7) | W8: =V8*(1+Assumptions!$F$7) | ... AG8: =AF8*(1+Assumptions!$F$7)
A9: Refunds and credits | D9: 0 | E9: 0 | F9: -52.5 | G9: 0 | H9: 0 | I9: 0 | J9: 0 | K9: 0 | L9: 0 | M9: -204.77 | N9: -107.9 | O9: -303.33 | P9: =P8*Assumptions!$F$9 | Q9: =Q8*Assumptions!$F$9 | R9: =R8*Assumptions!$F$9 | S9: =S8*Assumptions!$F$9 | T9: =T8*Assumptions!$F$9 | U9: =U8*Assumptions!$F$9 | V9: =V8*Assumptions!$F$9 | W9: =W8*Assumptions!$F$9 | ... AG9: =AG8*Assumptions!$F$9
A10: Services revenue | D10: 28628.07 | E10: 63288.07 | F10: 55518.07 | G10: 29488.07 | H10: 21677.65 | I10: 22331.4 | J10: 59871.4 | K10: 21421.4 | L10: 23396.4 | M10: 22996.4 | N10: 21740.15 | O10: 22911.4 | P10: =O10*(1+Assumptions!$F$8) | Q10: =P10*(1+Assumptions!$F$8) | R10: =Q10*(1+Assumptions!$F$8) | S10: =R10*(1+Assumptions!$F$8) | T10: =S10*(1+Assumptions!$F$8) | U10: =T10*(1+Assumptions!$F$8) | V10: =U10*(1+Assumptions!$F$8) | W10: =V10*(1+Assumptions!$F$8) | ... AG10: =AF10*(1+Assumptions!$F$8)
A11: Total revenue | D11: =SUM(D8:D10) | E11: =SUM(E8:E10) | F11: =SUM(F8:F10) | G11: =SUM(G8:G10) | H11: =SUM(H8:H10) | I11: =SUM(I8:I10) | J11: =SUM(J8:J10) | K11: =SUM(K8:K10) | ... AG11: =SUM(AG8:AG10)
A12: Cost of revenue
A13: GPU compute | D13: 302715.03 | E13: 295776.5 | F13: 287669.92 | G13: 433707.33 | H13: 408783.44 | I13: 457468.28 | J13: 436582.81 | K13: 440700.91 | L13: 434339.62 | M13: 439950.93 | N13: 436752.89 | O13: 469357.43 | P13: =P8*Assumptions!$F$10 | Q13: =Q8*Assumptions!$F$10 | R13: =R8*Assumptions!$F$10 | S13: =S8*Assumptions!$F$10 | T13: =T8*Assumptions!$F$10 | U13: =U8*Assumptions!$F$10 | V13: =V8*Assumptions!$F$10 | W13: =W8*Assumptions!$F$10 | ... AG13: =AG8*Assumptions!$F$10
A14: Hosting, payment fees and project costs | D14: 18945.61 | E14: 19402.96 | F14: 18037.49 | G14: 18806.63 | H14: 27234.54 | I14: 20424.84 | J14: 19352.12 | K14: 22284.03 | L14: 18854.54 | M14: 21788.88 | N14: 20815.27 | O14: 20532.18 | P14: =P11*Assumptions!$F$11 | Q14: =Q11*Assumptions!$F$11 | R14: =R11*Assumptions!$F$11 | S14: =S11*Assumptions!$F$11 | T14: =T11*Assumptions!$F$11 | U14: =U11*Assumptions!$F$11 | V14: =V11*Assumptions!$F$11 | W14: =W11*Assumptions!$F$11 | ... AG14: =AG11*Assumptions!$F$11
A15: Total cost of revenue | D15: =D13+D14 | E15: =E13+E14 | F15: =F13+F14 | G15: =G13+G14 | H15: =H13+H14 | I15: =I13+I14 | J15: =J13+J14 | K15: =K13+K14 | ... AG15: =AG13+AG14
A16: Gross profit | D16: =D11-D15 | E16: =E11-E15 | F16: =F11-F15 | G16: =G11-G15 | H16: =H11-H15 | I16: =I11-I15 | J16: =J11-J15 | K16: =K11-K15 | ... AG16: =AG11-AG15
A17: Gross margin | D17: =IF(D11=0,0,D16/D11) | E17: =IF(E11=0,0,E16/E11) | F17: =IF(F11=0,0,F16/F11) | G17: =IF(G11=0,0,G16/G11) | H17: =IF(H11=0,0,H16/H11) | I17: =IF(I11=0,0,I16/I11) | J17: =IF(J11=0,0,J16/J11) | K17: =IF(K11=0,0,K16/K11) | ... AG17: =IF(AG11=0,0,AG16/AG11)
A18: Operating expenses
A19: Payroll (salaries, payroll taxes, benefits) | D19: 695878.13 | E19: 719306.67 | F19: 742224.34 | G19: 775438.33 | H19: 763010.83 | I19: 811964.29 | J19: 834426.08 | K19: 834141.08 | L19: 834141.08 | M19: 854827.87 | N19: 854542.87 | O19: 854542.87 | P19: =O19+Assumptions!$C$28*Assumptions!$F$12 | Q19: =P19+Assumptions!$D$28*Assumptions!$F$12 | R19: =Q19+Assumptions!$E$28*Assumptions!$F$12 | S19: =R19+Assumptions!$F$28*Assumptions!$F$12 | T19: =S19+Assumptions!$G$28*Assumptions!$F$12 | U19: =T19+Assumptions!$H$28*Assumptions!$F$12 | V19: =U19+Assumptions!$I$28*Assumptions!$F$12 | W19: =V19+Assumptions!$J$28*Assumptions!$F$12 | X19: =W19+Assumptions!$K$28*Assumptions!$F$12 | Y19: =X19+Assumptions!$L$28*Assumptions!$F$12 | Z19: =Y19+Assumptions!$M$28*Assumptions!$F$12 | AA19: =Z19+Assumptions!$N$28*Assumptions!$F$12 | AB19: =AA19+Assumptions!$O$28*Assumptions!$F$12 | AC19: =AB19+Assumptions!$P$28*Assumptions!$F$12 | AD19: =AC19+Assumptions!$Q$28*Assumptions!$F$12 | AE19: =AD19+Assumptions!$R$28*Assumptions!$F$12 | AF19: =AE19+Assumptions!$S$28*Assumptions!$F$12 | AG19: =AF19+Assumptions!$T$28*Assumptions!$F$12
A20: Non-payroll opex (cloud R&D, software, rent, fees, marketing) | D20: 92574.45 | E20: 101623.18 | F20: 101636.73 | G20: 101765.04 | H20: 101611.63 | I20: 153625.32 | J20: 142822.01 | K20: 140996.55 | L20: 110806.92 | M20: 113110.1 | N20: 113106.82 | O20: 113133.2 | P20: =O20*(1+Assumptions!$F$13) | Q20: =P20*(1+Assumptions!$F$13) | R20: =Q20*(1+Assumptions!$F$13) | S20: =R20*(1+Assumptions!$F$13) | T20: =S20*(1+Assumptions!$F$13) | U20: =T20*(1+Assumptions!$F$13) | V20: =U20*(1+Assumptions!$F$13) | W20: =V20*(1+Assumptions!$F$13) | ... AG20: =AF20*(1+Assumptions!$F$13)
A21: Total operating expenses | D21: =D19+D20 | E21: =E19+E20 | F21: =F19+F20 | G21: =G19+G20 | H21: =H19+H20 | I21: =I19+I20 | J21: =J19+J20 | K21: =K19+K20 | ... AG21: =AG19+AG20
A22: EBITDA | D22: =D16-D21 | E22: =E16-E21 | F22: =F16-F21 | G22: =G16-G21 | H22: =H16-H21 | I22: =I16-I21 | J22: =J16-J21 | K22: =K16-K21 | ... AG22: =AG16-AG21
A23: Depreciation | D23: 30000 | E23: 30000 | F23: 35833.33 | G23: 35833.33 | H23: 35833.33 | I23: 35833.33 | J23: 35833.33 | K23: 54583.33 | L23: 54583.33 | M23: 54583.33 | N23: 54583.33 | O23: 57083.33 | P23: =$O$23 | Q23: =$O$23-SUM('Cash flow'!$P$15:'Cash flow'!P15)/Assumptions!$F$16 | R23: =$O$23-SUM('Cash flow'!$P$15:'Cash flow'!Q15)/Assumptions!$F$16 | S23: =$O$23-SUM('Cash flow'!$P$15:'Cash flow'!R15)/Assumptions!$F$16 | T23: =$O$23-SUM('Cash flow'!$P$15:'Cash flow'!S15)/Assumptions!$F$16 | U23: =$O$23-SUM('Cash flow'!$P$15:'Cash flow'!T15)/Assumptions!$F$16 | V23: =$O$23-SUM('Cash flow'!$P$15:'Cash flow'!U15)/Assumptions!$F$16 | W23: =$O$23-SUM('Cash flow'!$P$15:'Cash flow'!V15)/Assumptions!$F$16 | X23: =$O$23-SUM('Cash flow'!$P$15:'Cash flow'!W15)/Assumptions!$F$16 | ... AG23: =$O$23-SUM('Cash flow'!$P$15:'Cash flow'!AF15)/Assumptions!$F$16
A24: Operating income (EBIT) | D24: =D22-D23 | E24: =E22-E23 | F24: =F22-F23 | G24: =G22-G23 | H24: =H22-H23 | I24: =I22-I23 | J24: =J22-J23 | K24: =K22-K23 | ... AG24: =AG22-AG23
A25: Income tax | D25: 0 | E25: 0 | F25: 0 | G25: 0 | H25: 0 | I25: 0 | J25: 0 | K25: 0 | L25: 0 | M25: 0 | N25: 0 | O25: 0 | P25: =MAX(0,P24)*Assumptions!$F$20 | Q25: =MAX(0,Q24)*Assumptions!$F$20 | R25: =MAX(0,R24)*Assumptions!$F$20 | S25: =MAX(0,S24)*Assumptions!$F$20 | T25: =MAX(0,T24)*Assumptions!$F$20 | U25: =MAX(0,U24)*Assumptions!$F$20 | V25: =MAX(0,V24)*Assumptions!$F$20 | W25: =MAX(0,W24)*Assumptions!$F$20 | ... AG25: =MAX(0,AG24)*Assumptions!$F$20
A26: Net income | D26: =D24-D25 | E26: =E24-E25 | F26: =F24-F25 | G26: =G24-G25 | H26: =H24-H25 | I26: =I24-I25 | J26: =J24-J25 | K26: =K24-K25 | ... AG26: =AG24-AG25
A28: Memo
A29: Net income per the ledger (actuals) | D29: 60376.53 | E29: 38726.96 | F29: -14079.44 | G29: -14142.66 | H29: -64209.71 | I29: -47393.72 | J29: -65300.71 | K29: -130018.52 | L29: -102614.74 | M29: -130274.83 | N29: -134649.57 | O29: -70573.11
A30: Headcount (month end) | C30: 40 | D30: 41 | E30: 45 | F30: 46 | G30: 46 | H30: 46 | I30: 49 | J30: 51 | K30: 51 | L30: 51 | M30: 52 | N30: 52 | O30: 52 | P30: =O30+Assumptions!$C$27*Assumptions!$F$12 | Q30: =P30+Assumptions!$D$27*Assumptions!$F$12 | R30: =Q30+Assumptions!$E$27*Assumptions!$F$12 | S30: =R30+Assumptions!$F$27*Assumptions!$F$12 | T30: =S30+Assumptions!$G$27*Assumptions!$F$12 | U30: =T30+Assumptions!$H$27*Assumptions!$F$12 | V30: =U30+Assumptions!$I$27*Assumptions!$F$12 | W30: =V30+Assumptions!$J$27*Assumptions!$F$12 | X30: =W30+Assumptions!$K$27*Assumptions!$F$12 | Y30: =X30+Assumptions!$L$27*Assumptions!$F$12 | Z30: =Y30+Assumptions!$M$27*Assumptions!$F$12 | AA30: =Z30+Assumptions!$N$27*Assumptions!$F$12 | AB30: =AA30+Assumptions!$O$27*Assumptions!$F$12 | AC30: =AB30+Assumptions!$P$27*Assumptions!$F$12 | AD30: =AC30+Assumptions!$Q$27*Assumptions!$F$12 | AE30: =AD30+Assumptions!$R$27*Assumptions!$F$12 | AF30: =AE30+Assumptions!$S$27*Assumptions!$F$12 | AG30: =AF30+Assumptions!$T$27*Assumptions!$F$12

Sheet Balance sheet
A1: Echo Labs, Inc.
A2: Balance sheet
A3: Month-end balance sheet · actuals from the ledger (blue), forecast by formula (shaded) · USD
A5: USD | C5: 2025-09 | D5: 2025-10 | E5: 2025-11 | F5: 2025-12 | G5: 2026-01 | H5: 2026-02 | I5: 2026-03 | J5: 2026-04 | K5: 2026-05 | L5: 2026-06 | M5: 2026-07 | N5: 2026-08 | O5: 2026-09 | P5: 2026-10 | Q5: 2026-11 | R5: 2026-12 | S5: 2027-01 | T5: 2027-02 | U5: 2027-03 | V5: 2027-04 | W5: 2027-05 | X5: 2027-06 | Y5: 2027-07 | Z5: 2027-08 | AA5: 2027-09 | AB5: 2027-10 | AC5: 2027-11 | AD5: 2027-12 | AE5: 2028-01 | AF5: 2028-02 | AG5: 2028-03
C6: Opening | D6: Actual | E6: Actual | F6: Actual | G6: Actual | H6: Actual | I6: Actual | J6: Actual | K6: Actual | L6: Actual | M6: Actual | N6: Actual | O6: Actual | P6: Forecast | Q6: Forecast | R6: Forecast | S6: Forecast | T6: Forecast | U6: Forecast | V6: Forecast | W6: Forecast | X6: Forecast | Y6: Forecast | Z6: Forecast | AA6: Forecast | AB6: Forecast | AC6: Forecast | AD6: Forecast | AE6: Forecast | AF6: Forecast | AG6: Forecast
A7: Assets
A8: Cash | C8: 14147003 | D8: 13880463 | E8: 13344738 | F8: 14034441 | G8: 13768937 | H8: 13443374 | I8: 13688429 | J8: 12647290 | K8: 12487284 | L8: 12623782 | M8: 12610393 | N8: 12459729 | O8: 12356004 | P8: ='Cash flow'!P21 | Q8: ='Cash flow'!Q21 | R8: ='Cash flow'!R21 | S8: ='Cash flow'!S21 | T8: ='Cash flow'!T21 | U8: ='Cash flow'!U21 | V8: ='Cash flow'!V21 | W8: ='Cash flow'!W21 | ... AG8: ='Cash flow'!AG21
A9: Accounts receivable | C9: 1923464.4 | D9: 2360911.2 | E9: 2639856 | F9: 1958343.8 | G9: 2439168.5 | H9: 2857194.7 | I9: 2636823.4 | J9: 2787466.5 | K9: 2858499.1 | L9: 2671537.6 | M9: 2614032.5 | N9: 2596759.8 | O9: 2717039.8 | P9: ='P&L'!P11*Assumptions!$F$17/30 | Q9: ='P&L'!Q11*Assumptions!$F$17/30 | R9: ='P&L'!R11*Assumptions!$F$17/30 | S9: ='P&L'!S11*Assumptions!$F$17/30 | T9: ='P&L'!T11*Assumptions!$F$17/30 | U9: ='P&L'!U11*Assumptions!$F$17/30 | V9: ='P&L'!V11*Assumptions!$F$17/30 | W9: ='P&L'!W11*Assumptions!$F$17/30 | ... AG9: ='P&L'!AG11*Assumptions!$F$17/30
A10: Fixed assets at cost | C10: 1380000 | D10: 1380000 | E10: 1730000 | F10: 1730000 | G10: 1730000 | H10: 1730000 | I10: 1730000 | J10: 2630000 | K10: 2630000 | L10: 2630000 | M10: 2630000 | N10: 2720000 | O10: 2720000 | P10: =O10-'Cash flow'!P15 | Q10: =P10-'Cash flow'!Q15 | R10: =Q10-'Cash flow'!R15 | S10: =R10-'Cash flow'!S15 | T10: =S10-'Cash flow'!T15 | U10: =T10-'Cash flow'!U15 | V10: =U10-'Cash flow'!V15 | W10: =V10-'Cash flow'!W15 | ... AG10: =AF10-'Cash flow'!AG15
A11: Accumulated depreciation | C11: -115000 | D11: -145000 | E11: -175000 | F11: -210833.33 | G11: -246666.66 | H11: -282499.99 | I11: -318333.32 | J11: -354166.65 | K11: -408749.98 | L11: -463333.31 | M11: -517916.64 | N11: -572499.97 | O11: -629583.3 | P11: =O11-'P&L'!P23 | Q11: =P11-'P&L'!Q23 | R11: =Q11-'P&L'!R23 | S11: =R11-'P&L'!S23 | T11: =S11-'P&L'!T23 | U11: =T11-'P&L'!U23 | V11: =U11-'P&L'!V23 | W11: =V11-'P&L'!W23 | ... AG11: =AF11-'P&L'!AG23
A12: Total assets | C12: =SUM(C8:C11) | D12: =SUM(D8:D11) | E12: =SUM(E8:E11) | F12: =SUM(F8:F11) | G12: =SUM(G8:G11) | H12: =SUM(H8:H11) | I12: =SUM(I8:I11) | J12: =SUM(J8:J11) | ... AG12: =SUM(AG8:AG11)
A13: Liabilities
A14: Accounts payable | C14: 503890.49 | D14: 595981.9 | E14: 625196.21 | F14: 607758.04 | G14: 747200.19 | H14: 880467.53 | I14: 893331.61 | J14: 921980.09 | K14: 908726.6 | L14: 906294.99 | M14: 901267.33 | N14: 903682.2 | O14: 933726.62 | P14: =('P&L'!P15+'P&L'!P20)*Assumptions!$F$18/30 | Q14: =('P&L'!Q15+'P&L'!Q20)*Assumptions!$F$18/30 | R14: =('P&L'!R15+'P&L'!R20)*Assumptions!$F$18/30 | S14: =('P&L'!S15+'P&L'!S20)*Assumptions!$F$18/30 | T14: =('P&L'!T15+'P&L'!T20)*Assumptions!$F$18/30 | U14: =('P&L'!U15+'P&L'!U20)*Assumptions!$F$18/30 | V14: =('P&L'!V15+'P&L'!V20)*Assumptions!$F$18/30 | W14: =('P&L'!W15+'P&L'!W20)*Assumptions!$F$18/30 | ... AG14: =('P&L'!AG15+'P&L'!AG20)*Assumptions!$F$18/30
A15: Payroll taxes and benefits payable | C15: 327513.51 | D15: 315952.57 | E15: 311231.86 | F15: 315106.54 | G15: 369294.1 | H15: 356866.6 | I15: 380246.5 | J15: 390569.75 | K15: 390284.75 | L15: 390284.75 | M15: 400109.36 | N15: 399824.36 | O15: 399824.36 | P15: ='P&L'!P19*Assumptions!$F$19 | Q15: ='P&L'!Q19*Assumptions!$F$19 | R15: ='P&L'!R19*Assumptions!$F$19 | S15: ='P&L'!S19*Assumptions!$F$19 | T15: ='P&L'!T19*Assumptions!$F$19 | U15: ='P&L'!U19*Assumptions!$F$19 | V15: ='P&L'!V19*Assumptions!$F$19 | W15: ='P&L'!W19*Assumptions!$F$19 | ... AG15: ='P&L'!AG19*Assumptions!$F$19
A16: Total liabilities | C16: =C14+C15 | D16: =D14+D15 | E16: =E14+E15 | F16: =F14+F15 | G16: =G14+G15 | H16: =H14+H15 | I16: =I14+I15 | J16: =J14+J15 | ... AG16: =AG14+AG15
A17: Equity
A18: Preferred stock and paid-in capital | C18: 18000000 | D18: 18000000 | E18: 18000000 | F18: 18000000 | G18: 18000000 | H18: 18000000 | I18: 18000000 | J18: 18000000 | K18: 18000000 | L18: 18000000 | M18: 18000000 | N18: 18000000 | O18: 18000000 | P18: =O18+'Cash flow'!P17 | Q18: =P18+'Cash flow'!Q17 | R18: =Q18+'Cash flow'!R17 | S18: =R18+'Cash flow'!S17 | T18: =S18+'Cash flow'!T17 | U18: =T18+'Cash flow'!U17 | V18: =U18+'Cash flow'!V17 | W18: =V18+'Cash flow'!W17 | ... AG18: =AF18+'Cash flow'!AG17
A19: Retained earnings | C19: -1495937.1 | D19: -1435560.6 | E19: -1396833.6 | F19: -1410913.1 | G19: -1425055.7 | H19: -1489265.4 | I19: -1536659.1 | J19: -1601959.9 | K19: -1731978.4 | L19: -1834593.1 | M19: -1964867.9 | N19: -2099517.5 | O19: -2170090.6 | P19: =O19+'P&L'!P26 | Q19: =P19+'P&L'!Q26 | R19: =Q19+'P&L'!R26 | S19: =R19+'P&L'!S26 | T19: =S19+'P&L'!T26 | U19: =T19+'P&L'!U26 | V19: =U19+'P&L'!V26 | W19: =V19+'P&L'!W26 | ... AG19: =AF19+'P&L'!AG26
A20: Total equity | C20: =C18+C19 | D20: =D18+D19 | E20: =E18+E19 | F20: =F18+F19 | G20: =G18+G19 | H20: =H18+H19 | I20: =I18+I19 | J20: =J18+J19 | ... AG20: =AG18+AG19
A21: Total liabilities and equity | C21: =C16+C20 | D21: =D16+D20 | E21: =E16+E20 | F21: =F16+F20 | G21: =G16+G20 | H21: =H16+H20 | I21: =I16+I20 | J21: =J16+J20 | ... AG21: =AG16+AG20
A23: Check: assets - liabilities - equity (must be 0) | C23: =ROUND(C12-C21,2) | D23: =ROUND(D12-D21,2) | E23: =ROUND(E12-E21,2) | F23: =ROUND(F12-F21,2) | G23: =ROUND(G12-G21,2) | H23: =ROUND(H12-H21,2) | I23: =ROUND(I12-I21,2) | J23: =ROUND(J12-J21,2) | ... AG23: =ROUND(AG12-AG21,2)

Sheet Cash flow
A1: Echo Labs, Inc.
A2: Cash flow
A3: Indirect method, linked to the P&L and the balance sheet for every month (actuals included) · USD
A5: USD | C5: 2025-09 | D5: 2025-10 | E5: 2025-11 | F5: 2025-12 | G5: 2026-01 | H5: 2026-02 | I5: 2026-03 | J5: 2026-04 | K5: 2026-05 | L5: 2026-06 | M5: 2026-07 | N5: 2026-08 | O5: 2026-09 | P5: 2026-10 | Q5: 2026-11 | R5: 2026-12 | S5: 2027-01 | T5: 2027-02 | U5: 2027-03 | V5: 2027-04 | W5: 2027-05 | X5: 2027-06 | Y5: 2027-07 | Z5: 2027-08 | AA5: 2027-09 | AB5: 2027-10 | AC5: 2027-11 | AD5: 2027-12 | AE5: 2028-01 | AF5: 2028-02 | AG5: 2028-03
C6: Opening | D6: Actual | E6: Actual | F6: Actual | G6: Actual | H6: Actual | I6: Actual | J6: Actual | K6: Actual | L6: Actual | M6: Actual | N6: Actual | O6: Actual | P6: Forecast | Q6: Forecast | R6: Forecast | S6: Forecast | T6: Forecast | U6: Forecast | V6: Forecast | W6: Forecast | X6: Forecast | Y6: Forecast | Z6: Forecast | AA6: Forecast | AB6: Forecast | AC6: Forecast | AD6: Forecast | AE6: Forecast | AF6: Forecast | AG6: Forecast
A7: Operating activities
A8: Net income | D8: ='P&L'!D26 | E8: ='P&L'!E26 | F8: ='P&L'!F26 | G8: ='P&L'!G26 | H8: ='P&L'!H26 | I8: ='P&L'!I26 | J8: ='P&L'!J26 | K8: ='P&L'!K26 | ... AG8: ='P&L'!AG26
A9: Depreciation (non-cash, added back) | D9: ='P&L'!D23 | E9: ='P&L'!E23 | F9: ='P&L'!F23 | G9: ='P&L'!G23 | H9: ='P&L'!H23 | I9: ='P&L'!I23 | J9: ='P&L'!J23 | K9: ='P&L'!K23 | ... AG9: ='P&L'!AG23
A10: Change in accounts receivable | D10: ='Balance sheet'!C9-'Balance sheet'!D9 | E10: ='Balance sheet'!D9-'Balance sheet'!E9 | F10: ='Balance sheet'!E9-'Balance sheet'!F9 | G10: ='Balance sheet'!F9-'Balance sheet'!G9 | H10: ='Balance sheet'!G9-'Balance sheet'!H9 | I10: ='Balance sheet'!H9-'Balance sheet'!I9 | J10: ='Balance sheet'!I9-'Balance sheet'!J9 | K10: ='Balance sheet'!J9-'Balance sheet'!K9 | ... AG10: ='Balance sheet'!AF9-'Balance sheet'!AG9
A11: Change in accounts payable | D11: ='Balance sheet'!D14-'Balance sheet'!C14 | E11: ='Balance sheet'!E14-'Balance sheet'!D14 | F11: ='Balance sheet'!F14-'Balance sheet'!E14 | G11: ='Balance sheet'!G14-'Balance sheet'!F14 | H11: ='Balance sheet'!H14-'Balance sheet'!G14 | I11: ='Balance sheet'!I14-'Balance sheet'!H14 | J11: ='Balance sheet'!J14-'Balance sheet'!I14 | K11: ='Balance sheet'!K14-'Balance sheet'!J14 | ... AG11: ='Balance sheet'!AG14-'Balance sheet'!AF14
A12: Change in payroll liabilities | D12: ='Balance sheet'!D15-'Balance sheet'!C15 | E12: ='Balance sheet'!E15-'Balance sheet'!D15 | F12: ='Balance sheet'!F15-'Balance sheet'!E15 | G12: ='Balance sheet'!G15-'Balance sheet'!F15 | H12: ='Balance sheet'!H15-'Balance sheet'!G15 | I12: ='Balance sheet'!I15-'Balance sheet'!H15 | J12: ='Balance sheet'!J15-'Balance sheet'!I15 | K12: ='Balance sheet'!K15-'Balance sheet'!J15 | ... AG12: ='Balance sheet'!AG15-'Balance sheet'!AF15
A13: Cash from operations | D13: =SUM(D8:D12) | E13: =SUM(E8:E12) | F13: =SUM(F8:F12) | G13: =SUM(G8:G12) | H13: =SUM(H8:H12) | I13: =SUM(I8:I12) | J13: =SUM(J8:J12) | K13: =SUM(K8:K12) | ... AG13: =SUM(AG8:AG12)
A14: Investing activities
A15: Capital expenditure | D15: =-('Balance sheet'!D10-'Balance sheet'!C10) | E15: =-('Balance sheet'!E10-'Balance sheet'!D10) | F15: =-('Balance sheet'!F10-'Balance sheet'!E10) | G15: =-('Balance sheet'!G10-'Balance sheet'!F10) | H15: =-('Balance sheet'!H10-'Balance sheet'!G10) | I15: =-('Balance sheet'!I10-'Balance sheet'!H10) | J15: =-('Balance sheet'!J10-'Balance sheet'!I10) | K15: =-('Balance sheet'!K10-'Balance sheet'!J10) | ... O15: =-('Balance sheet'!O10-'Balance sheet'!N10) | P15: =-Assumptions!$F$15 | Q15: =-Assumptions!$F$15 | R15: =-Assumptions!$F$15 | S15: =-Assumptions!$F$15 | T15: =-Assumptions!$F$15 | U15: =-Assumptions!$F$15 | V15: =-Assumptions!$F$15 | W15: =-Assumptions!$F$15 | ... AG15: =-Assumptions!$F$15
A16: Financing activities
A17: Equity raised (enter a raise here) | D17: ='Balance sheet'!D18-'Balance sheet'!C18 | E17: ='Balance sheet'!E18-'Balance sheet'!D18 | F17: ='Balance sheet'!F18-'Balance sheet'!E18 | G17: ='Balance sheet'!G18-'Balance sheet'!F18 | H17: ='Balance sheet'!H18-'Balance sheet'!G18 | I17: ='Balance sheet'!I18-'Balance sheet'!H18 | J17: ='Balance sheet'!J18-'Balance sheet'!I18 | K17: ='Balance sheet'!K18-'Balance sheet'!J18 | ... O17: ='Balance sheet'!O18-'Balance sheet'!N18 | P17: 0 | Q17: 0 | R17: 0 | S17: 0 | T17: 0 | U17: 0 | V17: 0 | W17: 0 | X17: 0 | Y17: 0 | Z17: 0 | AA17: 0 | AB17: 0 | AC17: 0 | AD17: 0 | AE17: 0 | AF17: 0 | AG17: 0
A19: Net change in cash | D19: =D13+D15+D17 | E19: =E13+E15+E17 | F19: =F13+F15+F17 | G19: =G13+G15+G17 | H19: =H13+H15+H17 | I19: =I13+I15+I17 | J19: =J13+J15+J17 | K19: =K13+K15+K17 | ... AG19: =AG13+AG15+AG17
A20: Opening cash | D20: ='Balance sheet'!C8 | E20: ='Balance sheet'!D8 | F20: ='Balance sheet'!E8 | G20: ='Balance sheet'!F8 | H20: ='Balance sheet'!G8 | I20: ='Balance sheet'!H8 | J20: ='Balance sheet'!I8 | K20: ='Balance sheet'!J8 | ... AG20: ='Balance sheet'!AF8
A21: Closing cash | D21: =D20+D19 | E21: =E20+E19 | F21: =F20+F19 | G21: =G20+G19 | H21: =H20+H19 | I21: =I20+I19 | J21: =J20+J19 | K21: =K20+K19 | ... AG21: =AG20+AG19
A22: Free cash flow (operations + capex) | D22: =D13+D15 | E22: =E13+E15 | F22: =F13+F15 | G22: =G13+G15 | H22: =H13+H15 | I22: =I13+I15 | J22: =J13+J15 | K22: =K13+K15 | ... AG22: =AG13+AG15

Sheet KPIs
A1: Echo Labs, Inc.
A2: KPIs
A3: Runway, burn and unit economics, all by formula · USD unless stated
A5: USD | C5: 2025-09 | D5: 2025-10 | E5: 2025-11 | F5: 2025-12 | G5: 2026-01 | H5: 2026-02 | I5: 2026-03 | J5: 2026-04 | K5: 2026-05 | L5: 2026-06 | M5: 2026-07 | N5: 2026-08 | O5: 2026-09 | P5: 2026-10 | Q5: 2026-11 | R5: 2026-12 | S5: 2027-01 | T5: 2027-02 | U5: 2027-03 | V5: 2027-04 | W5: 2027-05 | X5: 2027-06 | Y5: 2027-07 | Z5: 2027-08 | AA5: 2027-09 | AB5: 2027-10 | AC5: 2027-11 | AD5: 2027-12 | AE5: 2028-01 | AF5: 2028-02 | AG5: 2028-03
C6: Opening | D6: Actual | E6: Actual | F6: Actual | G6: Actual | H6: Actual | I6: Actual | J6: Actual | K6: Actual | L6: Actual | M6: Actual | N6: Actual | O6: Actual | P6: Forecast | Q6: Forecast | R6: Forecast | S6: Forecast | T6: Forecast | U6: Forecast | V6: Forecast | W6: Forecast | X6: Forecast | Y6: Forecast | Z6: Forecast | AA6: Forecast | AB6: Forecast | AC6: Forecast | AD6: Forecast | AE6: Forecast | AF6: Forecast | AG6: Forecast
A7: Cash
A8: Cash at month end | C8: ='Balance sheet'!C8 | D8: ='Balance sheet'!D8 | E8: ='Balance sheet'!E8 | F8: ='Balance sheet'!F8 | G8: ='Balance sheet'!G8 | H8: ='Balance sheet'!H8 | I8: ='Balance sheet'!I8 | J8: ='Balance sheet'!J8 | ... AG8: ='Balance sheet'!AG8
A9: Net burn (cash used in the month) | D9: =-'Cash flow'!D19 | E9: =-'Cash flow'!E19 | F9: =-'Cash flow'!F19 | G9: =-'Cash flow'!G19 | H9: =-'Cash flow'!H19 | I9: =-'Cash flow'!I19 | J9: =-'Cash flow'!J19 | K9: =-'Cash flow'!K19 | ... AG9: =-'Cash flow'!AG19
A10: Average net burn, last 3 months | F10: =AVERAGE(D9:F9) | G10: =AVERAGE(E9:G9) | H10: =AVERAGE(F9:H9) | I10: =AVERAGE(G9:I9) | J10: =AVERAGE(H9:J9) | K10: =AVERAGE(I9:K9) | L10: =AVERAGE(J9:L9) | M10: =AVERAGE(K9:M9) | ... AG10: =AVERAGE(AE9:AG9)
A11: Runway (months) at the 3-month burn rate | F11: =IF(F10<=0,"cash generative",F8/F10) | G11: =IF(G10<=0,"cash generative",G8/G10) | H11: =IF(H10<=0,"cash generative",H8/H10) | I11: =IF(I10<=0,"cash generative",I8/I10) | J11: =IF(J10<=0,"cash generative",J8/J10) | K11: =IF(K10<=0,"cash generative",K8/K10) | L11: =IF(L10<=0,"cash generative",L8/L10) | M11: =IF(M10<=0,"cash generative",M8/M10) | ... AG11: =IF(AG10<=0,"cash generative",AG8/AG10)
A12: Cash above the minimum cash policy | C12: =C8-Assumptions!$F$21 | D12: =D8-Assumptions!$F$21 | E12: =E8-Assumptions!$F$21 | F12: =F8-Assumptions!$F$21 | G12: =G8-Assumptions!$F$21 | H12: =H8-Assumptions!$F$21 | I12: =I8-Assumptions!$F$21 | J12: =J8-Assumptions!$F$21 | ... AG12: =AG8-Assumptions!$F$21
A13: Customers and unit economics (same definitions as Finance OS)
A14: ARR (usage revenue x 12) | D14: ='P&L'!D8*12 | E14: ='P&L'!E8*12 | F14: ='P&L'!F8*12 | G14: ='P&L'!G8*12 | H14: ='P&L'!H8*12 | I14: ='P&L'!I8*12 | J14: ='P&L'!J8*12 | K14: ='P&L'!K8*12 | ... AG14: ='P&L'!AG8*12
A15: Sales and marketing spend (Sales department) | D15: 132660.4 | E15: 143707.59 | F15: 150667.76 | G15: 153176.56 | H15: 150611.56 | I15: 178329.31 | J15: 178822.98 | K15: 178822.98 | L15: 178822.98 | M15: 179489.65 | N15: 179489.65 | O15: 179489.65 | P15: ='P&L'!P21*Assumptions!$F$14 | Q15: ='P&L'!Q21*Assumptions!$F$14 | R15: ='P&L'!R21*Assumptions!$F$14 | S15: ='P&L'!S21*Assumptions!$F$14 | T15: ='P&L'!T21*Assumptions!$F$14 | U15: ='P&L'!U21*Assumptions!$F$14 | V15: ='P&L'!V21*Assumptions!$F$14 | W15: ='P&L'!W21*Assumptions!$F$14 | ... AG15: ='P&L'!AG21*Assumptions!$F$14
A16: New customers | D16: 7 | E16: 8 | F16: 4 | G16: 3 | H16: 1 | I16: 3 | J16: 4 | K16: 2 | L16: 6 | M16: 4 | N16: 3 | O16: 3 | P16: =Assumptions!$F$22 | Q16: =Assumptions!$F$22 | R16: =Assumptions!$F$22 | S16: =Assumptions!$F$22 | T16: =Assumptions!$F$22 | U16: =Assumptions!$F$22 | V16: =Assumptions!$F$22 | W16: =Assumptions!$F$22 | ... AG16: =Assumptions!$F$22
A17: Logo churn rate | D17: 0.0192 | E17: 0.0172 | F17: 0 | G17: 0.029 | H17: 0.0143 | I17: 0.0143 | J17: 0 | K17: 0.0263 | L17: 0.0526 | M17: 0.0385 | N17: 0.0759 | O17: 0.0649 | P17: =Assumptions!$F$23 | Q17: =Assumptions!$F$23 | R17: =Assumptions!$F$23 | S17: =Assumptions!$F$23 | T17: =Assumptions!$F$23 | U17: =Assumptions!$F$23 | V17: =Assumptions!$F$23 | W17: =Assumptions!$F$23 | ... AG17: =Assumptions!$F$23
A18: Active customers (month end) | D18: 58 | E18: 65 | F18: 69 | G18: 70 | H18: 70 | I18: 72 | J18: 76 | K18: 76 | L18: 78 | M18: 79 | N18: 77 | O18: 75 | P18: =O18*(1-P17)+P16 | Q18: =P18*(1-Q17)+Q16 | R18: =Q18*(1-R17)+R16 | S18: =R18*(1-S17)+S16 | T18: =S18*(1-T17)+T16 | U18: =T18*(1-U17)+U16 | V18: =U18*(1-V17)+V16 | W18: =V18*(1-W17)+W16 | ... AG18: =AF18*(1-AG17)+AG16
A19: ARPA (revenue per active customer, monthly) | D19: =IF(D18=0,0,'P&L'!D11/D18) | E19: =IF(E18=0,0,'P&L'!E11/E18) | F19: =IF(F18=0,0,'P&L'!F11/F18) | G19: =IF(G18=0,0,'P&L'!G11/G18) | H19: =IF(H18=0,0,'P&L'!H11/H18) | I19: =IF(I18=0,0,'P&L'!I11/I18) | J19: =IF(J18=0,0,'P&L'!J11/J18) | K19: =IF(K18=0,0,'P&L'!K11/K18) | ... AG19: =IF(AG18=0,0,'P&L'!AG11/AG18)
A20: CAC (S&M spend / new customers, trailing 3 months) | F20: =IF(SUM(D16:F16)=0,0,SUM(D15:F15)/SUM(D16:F16)) | G20: =IF(SUM(E16:G16)=0,0,SUM(E15:G15)/SUM(E16:G16)) | H20: =IF(SUM(F16:H16)=0,0,SUM(F15:H15)/SUM(F16:H16)) | I20: =IF(SUM(G16:I16)=0,0,SUM(G15:I15)/SUM(G16:I16)) | J20: =IF(SUM(H16:J16)=0,0,SUM(H15:J15)/SUM(H16:J16)) | K20: =IF(SUM(I16:K16)=0,0,SUM(I15:K15)/SUM(I16:K16)) | L20: =IF(SUM(J16:L16)=0,0,SUM(J15:L15)/SUM(J16:L16)) | M20: =IF(SUM(K16:M16)=0,0,SUM(K15:M15)/SUM(K16:M16)) | ... AG20: =IF(SUM(AE16:AG16)=0,0,SUM(AE15:AG15)/SUM(AE16:AG16))
A21: CAC payback (months) = CAC / (ARPA x gross margin) | F21: =IF(F19*'P&L'!F17=0,0,F20/(F19*'P&L'!F17)) | G21: =IF(G19*'P&L'!G17=0,0,G20/(G19*'P&L'!G17)) | H21: =IF(H19*'P&L'!H17=0,0,H20/(H19*'P&L'!H17)) | I21: =IF(I19*'P&L'!I17=0,0,I20/(I19*'P&L'!I17)) | J21: =IF(J19*'P&L'!J17=0,0,J20/(J19*'P&L'!J17)) | K21: =IF(K19*'P&L'!K17=0,0,K20/(K19*'P&L'!K17)) | L21: =IF(L19*'P&L'!L17=0,0,L20/(L19*'P&L'!L17)) | M21: =IF(M19*'P&L'!M17=0,0,M20/(M19*'P&L'!M17)) | ... AG21: =IF(AG19*'P&L'!AG17=0,0,AG20/(AG19*'P&L'!AG17))
A22: LTV (ARPA x gross margin / churn, trailing 3 months) | F22: =IF(AVERAGE(D17:F17)=0,0,F19*'P&L'!F17/AVERAGE(D17:F17)) | G22: =IF(AVERAGE(E17:G17)=0,0,G19*'P&L'!G17/AVERAGE(E17:G17)) | H22: =IF(AVERAGE(F17:H17)=0,0,H19*'P&L'!H17/AVERAGE(F17:H17)) | I22: =IF(AVERAGE(G17:I17)=0,0,I19*'P&L'!I17/AVERAGE(G17:I17)) | J22: =IF(AVERAGE(H17:J17)=0,0,J19*'P&L'!J17/AVERAGE(H17:J17)) | K22: =IF(AVERAGE(I17:K17)=0,0,K19*'P&L'!K17/AVERAGE(I17:K17)) | L22: =IF(AVERAGE(J17:L17)=0,0,L19*'P&L'!L17/AVERAGE(J17:L17)) | M22: =IF(AVERAGE(K17:M17)=0,0,M19*'P&L'!M17/AVERAGE(K17:M17)) | ... AG22: =IF(AVERAGE(AE17:AG17)=0,0,AG19*'P&L'!AG17/AVERAGE(AE17:AG17))
A23: LTV : CAC | F23: =IF(F20=0,0,F22/F20) | G23: =IF(G20=0,0,G22/G20) | H23: =IF(H20=0,0,H22/H20) | I23: =IF(I20=0,0,I22/I20) | J23: =IF(J20=0,0,J22/J20) | K23: =IF(K20=0,0,K22/K20) | L23: =IF(L20=0,0,L22/L20) | M23: =IF(M20=0,0,M22/M20) | ... AG23: =IF(AG20=0,0,AG22/AG20)
A24: CAC payback per Finance OS (actual months, for the tie-out) | F24: 1.8 | G24: 2.3 | H24: 4.8 | I24: 5.2 | J24: 5.1 | K24: 5 | L24: 3.9 | M24: 4 | N24: 3.6 | O24: 4.2
A25: Gross margin | D25: ='P&L'!D17 | E25: ='P&L'!E17 | F25: ='P&L'!F17 | G25: ='P&L'!G17 | H25: ='P&L'!H17 | I25: ='P&L'!I17 | J25: ='P&L'!J17 | K25: ='P&L'!K17 | ... AG25: ='P&L'!AG17
A26: EBITDA margin | D26: =IF('P&L'!D11=0,0,'P&L'!D22/'P&L'!D11) | E26: =IF('P&L'!E11=0,0,'P&L'!E22/'P&L'!E11) | F26: =IF('P&L'!F11=0,0,'P&L'!F22/'P&L'!F11) | G26: =IF('P&L'!G11=0,0,'P&L'!G22/'P&L'!G11) | H26: =IF('P&L'!H11=0,0,'P&L'!H22/'P&L'!H11) | I26: =IF('P&L'!I11=0,0,'P&L'!I22/'P&L'!I11) | J26: =IF('P&L'!J11=0,0,'P&L'!J22/'P&L'!J11) | K26: =IF('P&L'!K11=0,0,'P&L'!K22/'P&L'!K11) | ... AG26: =IF('P&L'!AG11=0,0,'P&L'!AG22/'P&L'!AG11)

Sheet Checks
A1: Echo Labs, Inc.
A2: Checks
A3: Every check is a formula; TRUE in every month means the model is internally consistent
A5: USD | C5: 2025-09 | D5: 2025-10 | E5: 2025-11 | F5: 2025-12 | G5: 2026-01 | H5: 2026-02 | I5: 2026-03 | J5: 2026-04 | K5: 2026-05 | L5: 2026-06 | M5: 2026-07 | N5: 2026-08 | O5: 2026-09 | P5: 2026-10 | Q5: 2026-11 | R5: 2026-12 | S5: 2027-01 | T5: 2027-02 | U5: 2027-03 | V5: 2027-04 | W5: 2027-05 | X5: 2027-06 | Y5: 2027-07 | Z5: 2027-08 | AA5: 2027-09 | AB5: 2027-10 | AC5: 2027-11 | AD5: 2027-12 | AE5: 2028-01 | AF5: 2028-02 | AG5: 2028-03
C6: Opening | D6: Actual | E6: Actual | F6: Actual | G6: Actual | H6: Actual | I6: Actual | J6: Actual | K6: Actual | L6: Actual | M6: Actual | N6: Actual | O6: Actual | P6: Forecast | Q6: Forecast | R6: Forecast | S6: Forecast | T6: Forecast | U6: Forecast | V6: Forecast | W6: Forecast | X6: Forecast | Y6: Forecast | Z6: Forecast | AA6: Forecast | AB6: Forecast | AC6: Forecast | AD6: Forecast | AE6: Forecast | AF6: Forecast | AG6: Forecast
A7: Integrity checks (TRUE = pass)
A8: Balance sheet balances (assets = liabilities + equity) | C8: =ABS('Balance sheet'!C23)<0.01 | D8: =ABS('Balance sheet'!D23)<0.01 | E8: =ABS('Balance sheet'!E23)<0.01 | F8: =ABS('Balance sheet'!F23)<0.01 | G8: =ABS('Balance sheet'!G23)<0.01 | H8: =ABS('Balance sheet'!H23)<0.01 | I8: =ABS('Balance sheet'!I23)<0.01 | J8: =ABS('Balance sheet'!J23)<0.01 | ... AG8: =ABS('Balance sheet'!AG23)<0.01
A9: Cash flow closing cash = balance sheet cash | D9: =ABS('Cash flow'!D21-'Balance sheet'!D8)<0.01 | E9: =ABS('Cash flow'!E21-'Balance sheet'!E8)<0.01 | F9: =ABS('Cash flow'!F21-'Balance sheet'!F8)<0.01 | G9: =ABS('Cash flow'!G21-'Balance sheet'!G8)<0.01 | H9: =ABS('Cash flow'!H21-'Balance sheet'!H8)<0.01 | I9: =ABS('Cash flow'!I21-'Balance sheet'!I8)<0.01 | J9: =ABS('Cash flow'!J21-'Balance sheet'!J8)<0.01 | K9: =ABS('Cash flow'!K21-'Balance sheet'!K8)<0.01 | ... AG9: =ABS('Cash flow'!AG21-'Balance sheet'!AG8)<0.01
A10: Cash flow starts from P&L net income | D10: =ABS('Cash flow'!D8-'P&L'!D26)<0.01 | E10: =ABS('Cash flow'!E8-'P&L'!E26)<0.01 | F10: =ABS('Cash flow'!F8-'P&L'!F26)<0.01 | G10: =ABS('Cash flow'!G8-'P&L'!G26)<0.01 | H10: =ABS('Cash flow'!H8-'P&L'!H26)<0.01 | I10: =ABS('Cash flow'!I8-'P&L'!I26)<0.01 | J10: =ABS('Cash flow'!J8-'P&L'!J26)<0.01 | K10: =ABS('Cash flow'!K8-'P&L'!K26)<0.01 | ... AG10: =ABS('Cash flow'!AG8-'P&L'!AG26)<0.01
A11: P&L net income ties to the ledger (actual months) | D11: =ABS('P&L'!D26-'P&L'!D29)<0.01 | E11: =ABS('P&L'!E26-'P&L'!E29)<0.01 | F11: =ABS('P&L'!F26-'P&L'!F29)<0.01 | G11: =ABS('P&L'!G26-'P&L'!G29)<0.01 | H11: =ABS('P&L'!H26-'P&L'!H29)<0.01 | I11: =ABS('P&L'!I26-'P&L'!I29)<0.01 | J11: =ABS('P&L'!J26-'P&L'!J29)<0.01 | K11: =ABS('P&L'!K26-'P&L'!K29)<0.01 | ... O11: =ABS('P&L'!O26-'P&L'!O29)<0.01
A12: CAC payback ties to Finance OS (actual months) | F12: =ABS(ROUND(KPIs!F21,1)-KPIs!F24)<0.15 | G12: =ABS(ROUND(KPIs!G21,1)-KPIs!G24)<0.15 | H12: =ABS(ROUND(KPIs!H21,1)-KPIs!H24)<0.15 | I12: =ABS(ROUND(KPIs!I21,1)-KPIs!I24)<0.15 | J12: =ABS(ROUND(KPIs!J21,1)-KPIs!J24)<0.15 | K12: =ABS(ROUND(KPIs!K21,1)-KPIs!K24)<0.15 | L12: =ABS(ROUND(KPIs!L21,1)-KPIs!L24)<0.15 | M12: =ABS(ROUND(KPIs!M21,1)-KPIs!M24)<0.15 | ... O12: =ABS(ROUND(KPIs!O21,1)-KPIs!O24)<0.15
A13: Retained earnings roll forward by net income | D13: =ABS('Balance sheet'!D19-'Balance sheet'!C19-'P&L'!D26)<0.01 | E13: =ABS('Balance sheet'!E19-'Balance sheet'!D19-'P&L'!E26)<0.01 | F13: =ABS('Balance sheet'!F19-'Balance sheet'!E19-'P&L'!F26)<0.01 | G13: =ABS('Balance sheet'!G19-'Balance sheet'!F19-'P&L'!G26)<0.01 | H13: =ABS('Balance sheet'!H19-'Balance sheet'!G19-'P&L'!H26)<0.01 | I13: =ABS('Balance sheet'!I19-'Balance sheet'!H19-'P&L'!I26)<0.01 | J13: =ABS('Balance sheet'!J19-'Balance sheet'!I19-'P&L'!J26)<0.01 | K13: =ABS('Balance sheet'!K19-'Balance sheet'!J19-'P&L'!K26)<0.01 | ... AG13: =ABS('Balance sheet'!AG19-'Balance sheet'!AF19-'P&L'!AG26)<0.01
A14: All checks pass this month | C14: =C8 | D14: =AND(D8:D13) | E14: =AND(E8:E13) | F14: =AND(F8:F13) | G14: =AND(G8:G13) | H14: =AND(H8:H13) | I14: =AND(I8:I13) | J14: =AND(J8:J13) | K14: =AND(K8:K13) | ... AG14: =AND(AG8:AG13)
A16: Model status | C16: =IF(COUNTIF(C14:AG14,FALSE)=0,"ALL CHECKS PASS","CHECK FAILED")
A17: Months failing a check | C17: =COUNTIF(C14:AG14,FALSE)

Sheet Annual summary
A1: Echo Labs, Inc.
A2: Annual summary
A3: Full calendar years in the model; each figure sums or picks the monthly columns, so it follows the scenario.
A5: USD | C5: FY2026 | D5: FY2027
C6: 9 actual + 3 forecast | D6: forecast
A7: Revenue | C7: =SUM('P&L'!G11:R11) | D7: =SUM('P&L'!S11:AD11)
A8: Gross profit | C8: =SUM('P&L'!G16:R16) | D8: =SUM('P&L'!S16:AD16)
A9: Gross margin | C9: =IF(C7=0,0,C8/C7) | D9: =IF(D7=0,0,D8/D7)
A10: Operating expenses | C10: =SUM('P&L'!G21:R21) | D10: =SUM('P&L'!S21:AD21)
A11: EBITDA | C11: =SUM('P&L'!G22:R22) | D11: =SUM('P&L'!S22:AD22)
A12: EBITDA margin | C12: =IF(C7=0,0,C11/C7) | D12: =IF(D7=0,0,D11/D7)
A13: Net income | C13: =SUM('P&L'!G26:R26) | D13: =SUM('P&L'!S26:AD26)
A14: Cash from operations | C14: =SUM('Cash flow'!G13:R13) | D14: =SUM('Cash flow'!S13:AD13)
A15: Capital expenditure | C15: =SUM('Cash flow'!G15:R15) | D15: =SUM('Cash flow'!S15:AD15)
A16: Free cash flow | C16: =SUM('Cash flow'!G22:R22) | D16: =SUM('Cash flow'!S22:AD22)
A17: Cash at year end | C17: ='Balance sheet'!R8 | D17: ='Balance sheet'!AD8
A18: ARR at year end | C18: ='KPIs'!R14 | D18: ='KPIs'!AD14
A19: Active customers at year end | C19: ='KPIs'!R18 | D19: ='KPIs'!AD18
A20: Headcount at year end | C20: ='P&L'!R30 | D20: ='P&L'!AD30
A21: CAC payback at year end (months) | C21: ='KPIs'!R21 | D21: ='KPIs'!AD21

Sheet Sensitivity
A1: Echo Labs, Inc.
A2: Sensitivity: cash at the end of the forecast
A3: An Excel Data Table (Data > What-If Analysis > Data Table): Excel reruns the whole model for each pair of usage growth (down) and non-payroll opex growth (across), with the selected scenario's other drivers. Leave C5 and C6 blank: they are the table's input cells.
A5: Usage growth override (the table's column input cell)
A6: Non-payroll opex growth override (the table's row input cell)
A8: Cash at the end of the forecast (down: usage growth per month; across: non-payroll opex growth per month)
B9: ='Balance sheet'!AG8 | C9: 0 | D9: 0.01 | E9: 0.02 | F9: 0.03
B10: 0
B11: 0.01
B12: 0.02
B13: 0.03
B14: 0.04
A16: Google Sheets does not support data tables, so there the grid stays empty; the Finance OS web view fills it by recalculating the model for each pair.
